{"cameraMode":{"drawMode":0,"name":"Shaded","section":"Shading Mode"},"sceneLighting":true,"audioPlay":false,"sceneViewState":{"m_AlwaysRefresh":false,"showFog":true,"showSkybox":true,"showFlares":true,"showImageEffects":true,"showParticleSystems":true,"showVisualEffectGraphs":true,"m_FxEnabled":true},"in2DMode":false,"pivot":{"x":-0.965632438659668,"y":2.9453158378601076,"z":1.7311081886291505},"rotation":{"x":0.16654442250728608,"y":0.5764952898025513,"z":-0.12143018841743469,"w":0.7906793355941773},"size":8.870673179626465,"orthographic":false}